{"card_name": "Stunted By Success", "color": "W", "rarity": "common", "type": "Enchantment", "number": 30, "color_identity": "W", "cost": "{3}{W}", "rules_text": "Affinity for legendary permanents [i](This spell costs {1} less to cast for each legendary permanent you control.)[/i]\nWhen this enchantment enters, exile target nonland permanent an opponent controls until this enchantment leaves the battlefield.", "flavor_text": "[i][/i]", "pt": "", "special_text": "", "shape": "normal", "set": "POP2", "loyalty": "", "artist": "Kez Laczin", "notes": "https://www.artstation.com/artwork/9m0EEy", "image_type": "png"}